Metadata-Version: 2.1
Name: Logic-Circuits-Evolution
Version: 1.0.4
Summary: Modulo Python dedicado a evolução de circuitos lógicos através de algoritmos genéticos
Author: Humberto Távora, Stefan Blawid, Yasmin Maria
License: UNKNOWN
Platform: UNKNOWN
